[
    {
        "title": "“I love this app a little more every day.”"
    },
    {
        "title": "“Oh, hey. Welcome to my TikTok.”"
    },
    {
        "title": "“Not your average e-girl or e-boy.”"
    },
    {
        "title": "“Tap, tap, tap. Is this thing on?”"
    },
    {
        "title": "“Just drawing hearts on my face and making vids.”"
    },
    {
        "title": "“Like and subscribe. Wait, this is TikTok never mind.”"
    },
    {
        "title": "“In the wise words of blink-182, what’s my age again?”"
    },
    {
        "title": "“Just a small town girl making it big in the Internet world.”"
    },
    {
        "title": "“When in doubt, laugh it out.”"
    },
    {
        "title": "“Now serving looks and vibes.”"
    },
    {
        "title": "Used to think I was a tad indecisive, but now I’m not quite sure"
    },
    {
        "title": " Life is short so I’m smiling while I’ve still got all my teeth"
    },
    {
        "title": " “Was too busy having fun to post this one.”"
    },
    {
        "title": " “Time flies when you’re having too much fun.”"
    },
    {
        "title": " “I never wanted last night to end.”"
    },
    {
        "title": " “Can we do that all over again?”"
    },
    {
        "title": " Relationship status: Netflix and ice cream"
    },
    {
        "title": " The bags under my eyes are Chanel"
    },
    {
        "title": " “Good nights and even better company.”"
    },
    {
        "title": " “Life’s too short to post your photo on the same day that it"
    },
    {
        "title": " happened.”"
    },
    {
        "title": " I’d rather steal your dessert than your boyfriend"
    },
    {
        "title": " Sassy, classy with a touch of badassy"
    },
    {
        "title": " One day, I hope to become a grown up"
    },
    {
        "title": " My hobbies are breakfast, lunch, and dinner topped with a chocolate dessert"
    },
    {
        "title": " Instagram bio currently loading"
    },
    {
        "title": " “Live for the moments you can’t put in words.”"
    },
    {
        "title": " “Crazy nights make the best memories.”"
    },
    {
        "title": " “I can’t focus on today, still thinking about last night.”"
    },
    {
        "title": " “Here’s to the nights that turned into mornings and the friends who"
    },
    {
        "title": " turned into family.”"
    },
    {
        "title": "“I love this app a little more every day.”"
    },
    {
        "title": "“Oh, hey. Welcome to my TikTok.”"
    },
    {
        "title": "“Not your average e-girl or e-boy.”"
    },
    {
        "title": "“Tap, tap, tap. Is this thing on?”"
    },
    {
        "title": "“Just drawing hearts on my face and making vids.”"
    },
    {
        "title": "“Like and subscribe. Wait, this is TikTok never mind.”"
    },
    {
        "title": "“In the wise words of blink-182, what’s my age again?”"
    },
    {
        "title": "“Just a small town girl making it big in the Internet world.”"
    },
    {
        "title": "“When in doubt, laugh it out.”"
    },
    {
        "title": "“Now serving looks and vibes.”"
    },
    {
        "title": "Used to think I was a tad indecisive, but now I’m not quite sure"
    },
    {
        "title": " Life is short so I’m smiling while I’ve still got all my teeth"
    },
    {
        "title": " “Was too busy having fun to post this one.”"
    },
    {
        "title": " “Time flies when you’re having too much fun.”"
    },
    {
        "title": " “I never wanted last night to end.”"
    },
    {
        "title": " “Can we do that all over again?”"
    },
    {
        "title": " Relationship status: Netflix and ice cream"
    },
    {
        "title": " The bags under my eyes are Chanel"
    },
    {
        "title": " “Good nights and even better company.”"
    },
    {
        "title": " “Life’s too short to post your photo on the same day that it"
    },
    {
        "title": " happened.”"
    },
    {
        "title": " I’d rather steal your dessert than your boyfriend"
    },
    {
        "title": " Sassy, classy with a touch of badassy"
    },
    {
        "title": " One day, I hope to become a grown up"
    },
    {
        "title": " My hobbies are breakfast, lunch, and dinner topped with a chocolate dessert"
    },
    {
        "title": " Instagram bio currently loading"
    },
    {
        "title": " “Live for the moments you can’t put in words.”"
    },
    {
        "title": " “Crazy nights make the best memories.”"
    },
    {
        "title": " “I can’t focus on today, still thinking about last night.”"
    },
    {
        "title": " “Here’s to the nights that turned into mornings and the friends who"
    },
    {
        "title": " turned into family.”"
    }
]